Metadata-Version: 2.1
Name: pykoges
Version: 0.5.0
Summary: Python module for cohort data reading
Home-page: https://github.com/oculi-s/pykoges
Author: oculis
Author-email: oculis0925@yonsei.ac.kr
